pyiir/__init__.py
pyiir/pyiir.py
pyiir-0.0.7.dist-info/METADATA
pyiir-0.0.7.dist-info/WHEEL
pyiir-0.0.7.dist-info/top_level.txt
pyiir-0.0.7.dist-info/RECORD
