Metadata-Version: 2.1
Name: pyiir
Version: 0.0.7
Summary: Wrapper around IIR
Home-page: https://github.com/aeorxc/pyiir
Author: jalex1
License: UNKNOWN
Project-URL: Source, https://github.com/aeorxc/pyiir
Platform: UNKNOWN
Classifier: Programming Language :: Python :: 3
Classifier: License :: OSI Approved :: MIT License
Classifier: Operating System :: OS Independent
Requires-Python: >=3.8
Requires-Dist: requests
Requires-Dist: cachetools
Requires-Dist: pandas
